thirty_days_of_pyai_helpers-0.1.34.dist-info/licenses/LICENSE
thirty_days_pyai_helpers/__init__.py
thirty_days_pyai_helpers/intro_designs.py
thirty_days_pyai_helpers/print.py
thirty_days_of_pyai_helpers-0.1.34.dist-info/METADATA
thirty_days_of_pyai_helpers-0.1.34.dist-info/WHEEL
thirty_days_of_pyai_helpers-0.1.34.dist-info/top_level.txt
thirty_days_of_pyai_helpers-0.1.34.dist-info/RECORD
