Metadata-Version: 2.4
Name: thirty-days-of-pyai-helpers
Version: 0.1.34
Summary: 30 Days of AI with Python Course helper functions.
Author: Witeout Codes
Author-email: info@loveyourvecino.com
License: MIT
Classifier: Programming Language :: Python :: 3
Classifier: License :: OSI Approved :: MIT License
Classifier: Operating System :: OS Independent
Requires-Python: >=3.6
License-File: LICENSE
Requires-Dist: colorama==0.4.6
Provides-Extra: dev
Requires-Dist: pytest==7.1.2; extra == "dev"
Dynamic: author
Dynamic: author-email
Dynamic: classifier
Dynamic: description
Dynamic: description-content-type
Dynamic: license
Dynamic: license-file
Dynamic: provides-extra
Dynamic: requires-dist
Dynamic: requires-python
Dynamic: summary
